{
	"backtrace" : 0,
	"backtraceGraph" : 
	{
		"commands" : [],
		"files" : 
		[
			"4/CMakeLists.txt"
		],
		"nodes" : 
		[
			{
				"file" : 0
			}
		]
	},
	"id" : "4_autogen::@b410677b84ed73fac43f",
	"isGeneratorProvided" : true,
	"name" : "4_autogen",
	"paths" : 
	{
		"build" : "4",
		"source" : "4"
	},
	"sourceGroups" : 
	[
		{
			"name" : "",
			"sourceIndexes" : 
			[
				0
			]
		},
		{
			"name" : "CMake Rules",
			"sourceIndexes" : 
			[
				1
			]
		}
	],
	"sources" : 
	[
		{
			"backtrace" : 0,
			"isGenerated" : true,
			"path" : "build/4/CMakeFiles/4_autogen",
			"sourceGroupIndex" : 0
		},
		{
			"backtrace" : 0,
			"isGenerated" : true,
			"path" : "build/4/CMakeFiles/4_autogen.rule",
			"sourceGroupIndex" : 1
		}
	],
	"type" : "UTILITY"
}
